{
  "questIDHigh:4": -5353291742575900958,
  "preRequisites:9": {
    "0:10": {
      "questIDHigh:4": 0,
      "questIDLow:4": 2675
    },
    "1:10": {
      "questIDHigh:4": 6250663031082139962,
      "questIDLow:4": -7488873106708724551
    }
  },
  "questIDLow:4": -7266008273438198017,
  "properties:10": {
    "betterquesting:10": {
      "snd_complete:8": "random.levelup",
      "taskLogic:8": "AND",
      "visibility:8": "NORMAL",
      "isMain:1": 0,
      "simultaneous:1": 0,
      "icon:10": {
        "id:8": "Botania:pool",
        "Count:3": 1,
        "Damage:2": 1,
        "OreDict:8": ""
      },
      "snd_update:8": "random.levelup",
      "repeatTime:3": -1,
      "globalShare:1": 0,
      "questLogic:8": "AND",
      "repeat_relative:1": 1,
      "name:8": "Unlimited Maaaaanaaaaa",
      "lockedProgress:1": 0,
      "autoClaim:1": 0,
      "isSilent:1": 0,
      "desc:8": "Trying to get a max rank terrashatterer and standard mana generation methods just aren\u0027t doing it for you? Simply harness the power of infinity to create a mana pool that never runs out. Also comes in a handy infinite mana tablet form for personal use with ring of Loki to really maximize that multiblock spam later."
    }
  },
  "tasks:9": {
    "0:10": {
      "partialMatch:1": 1,
      "autoConsume:1": 0,
      "groupDetect:1": 0,
      "ignoreNBT:1": 1,
      "index:3": 0,
      "consume:1": 0,
      "requiredItems:9": {
        "0:10": {
          "id:8": "Botania:pool",
          "Count:3": 1,
          "Damage:2": 1,
          "OreDict:8": ""
        }
      },
      "taskID:8": "bq_standard:retrieval"
    },
    "1:10": {
      "partialMatch:1": 1,
      "autoConsume:1": 0,
      "groupDetect:1": 0,
      "ignoreNBT:1": 1,
      "index:3": 1,
      "consume:1": 0,
      "requiredItems:9": {
        "0:10": {
          "id:8": "Botania:manaTablet",
          "Count:3": 1,
          "tag:10": {
            "mana:3": 500000,
            "creative:1": 1
          },
          "Damage:2": 0,
          "OreDict:8": ""
        }
      },
      "taskID:8": "bq_standard:optional_retrieval"
    }
  },
  "rewards:9": {
    "0:10": {
      "rewardID:8": "bq_standard:item",
      "index:3": 0,
      "rewards:9": {
        "0:10": {
          "id:8": "Botania:blackLotus",
          "Count:3": 16,
          "Damage:2": 0,
          "OreDict:8": ""
        },
        "1:10": {
          "id:8": "Botania:blackLotus",
          "Count:3": 16,
          "Damage:2": 1,
          "OreDict:8": ""
        }
      }
    }
  }
}